odoo8_addon_connector_ecommerce-8.0.3.0.0.99.dev3-py2.7-nspkg.pth
odoo8_addon_connector_ecommerce-8.0.3.0.0.99.dev3.dist-info/METADATA
odoo8_addon_connector_ecommerce-8.0.3.0.0.99.dev3.dist-info/RECORD
odoo8_addon_connector_ecommerce-8.0.3.0.0.99.dev3.dist-info/WHEEL
odoo8_addon_connector_ecommerce-8.0.3.0.0.99.dev3.dist-info/namespace_packages.txt
odoo8_addon_connector_ecommerce-8.0.3.0.0.99.dev3.dist-info/top_level.txt
odoo_addons/connector_ecommerce/README.rst
odoo_addons/connector_ecommerce/__init__.py
odoo_addons/connector_ecommerce/__openerp__.py
odoo_addons/connector_ecommerce/account.py
odoo_addons/connector_ecommerce/account_view.xml
odoo_addons/connector_ecommerce/ecommerce_data.xml
odoo_addons/connector_ecommerce/event.py
odoo_addons/connector_ecommerce/invoice.py
odoo_addons/connector_ecommerce/invoice_view.xml
odoo_addons/connector_ecommerce/payment_method.py
odoo_addons/connector_ecommerce/payment_method_view.xml
odoo_addons/connector_ecommerce/product.py
odoo_addons/connector_ecommerce/sale.py
odoo_addons/connector_ecommerce/sale_view.xml
odoo_addons/connector_ecommerce/stock.py
odoo_addons/connector_ecommerce/stock_view.xml
odoo_addons/connector_ecommerce/i18n/de.po
odoo_addons/connector_ecommerce/i18n/es.po
odoo_addons/connector_ecommerce/i18n/fr.po
odoo_addons/connector_ecommerce/i18n/nl.po
odoo_addons/connector_ecommerce/security/ir.model.access.csv
odoo_addons/connector_ecommerce/security/security.xml
odoo_addons/connector_ecommerce/static/description/icon.png
odoo_addons/connector_ecommerce/tests/__init__.py
odoo_addons/connector_ecommerce/tests/test_invoice_event.py
odoo_addons/connector_ecommerce/tests/test_onchange.py
odoo_addons/connector_ecommerce/tests/test_picking_event.py
odoo_addons/connector_ecommerce/unit/__init__.py
odoo_addons/connector_ecommerce/unit/sale_order_onchange.py
odoo_addons/connector_ecommerce/wizard/__init__.py
odoo_addons/connector_ecommerce/wizard/sale_ignore_cancel.py
odoo_addons/connector_ecommerce/wizard/sale_ignore_cancel_view.xml
