Metadata-Version: 2.1
Name: odoo8-addon-connector-ecommerce
Version: 8.0.3.0.0.99.dev3
Summary: Connector for E-Commerce
Home-page: http://openerp-connector.com
Author: Camptocamp,Akretion,Odoo Community Association (OCA)
Author-email: support@odoo-community.org
License: AGPL-3
Platform: UNKNOWN
Classifier: Programming Language :: Python
Classifier: Framework :: Odoo
Classifier: License :: OSI Approved :: GNU Affero General Public License v3
Requires-Python: ~=2.7
Requires-Dist: odoo8-addon-connector
Requires-Dist: odoo8-addon-connector-base-product
Requires-Dist: odoo8-addon-sale-exceptions
Requires-Dist: odoo8-addon-sale-payment-method-automatic-workflow
Requires-Dist: odoo (<9.0a,>=8.0a)
